hyperargs/__init__.py
hyperargs/args.py
hyperargs/conf.py
hyperargs/utils.py
hyperargs-0.1.2.dist-info/METADATA
hyperargs-0.1.2.dist-info/WHEEL
hyperargs-0.1.2.dist-info/licenses/LICENSE
hyperargs-0.1.2.dist-info/RECORD
