Metadata-Version: 2.4
Name: HyperArgs
Version: 0.1.2
Summary: HyperArgs is a typed configuration library with automatic WEB GUI for Python.
Project-URL: Homepage, https://github.com/TYTTYTTYT/HyperArgs
Project-URL: Bug Tracker, https://github.com/TYTTYTTYT/HyperArgs/issues
Project-URL: repository, https://github.com/TYTTYTTYT/HyperArgs.git
Author-email: Yintao Tai <tai.yintao@gmail.com>
License-File: LICENSE
Classifier: Development Status :: 2 - Pre-Alpha
Classifier: Intended Audience :: Developers
Classifier: Intended Audience :: Education
Classifier: Intended Audience :: End Users/Desktop
Classifier: Intended Audience :: Information Technology
Classifier: Intended Audience :: Science/Research
Classifier: License :: OSI Approved :: Apache Software License
Classifier: Operating System :: OS Independent
Classifier: Programming Language :: Python :: 3
Classifier: Topic :: Scientific/Engineering :: Artificial Intelligence
Classifier: Topic :: Scientific/Engineering :: Human Machine Interfaces
Classifier: Topic :: Software Development :: Libraries :: Python Modules
Classifier: Topic :: Software Development :: User Interfaces
Classifier: Topic :: Utilities
Classifier: Typing :: Typed
Requires-Python: >=3.10
Requires-Dist: networkx>=3.0
Requires-Dist: pyyaml>=6.0
Requires-Dist: streamlit>=1.50.0
Requires-Dist: tomli-w>=1.0.0
Requires-Dist: tomli>=2.0.0
Requires-Dist: typing-extensions>=4.0.0
